valdazpack/__init__.py
valdazpack/__main__.py
valdazpack/data/daz/audiences.txt
valdazpack/data/daz/common_content_directories.txt
valdazpack/data/daz/deprecated_categories.txt
valdazpack/data/daz/deprecated_content_types.txt
valdazpack/data/daz/dson_external_file_references.txt
valdazpack/data/daz/expected_runtime_directories.txt
valdazpack/data/daz/import_file_extensions.txt
valdazpack/data/daz/native_file_extensions.txt
valdazpack/data/daz/reserved_package_prefixes.txt
valdazpack/data/daz/special_categories.txt
valdazpack/data/daz/user_facing_excluded_directories.txt
valdazpack/data/poser/expected_libraries_directories.txt
valdazpack/data/poser/expected_runtime_directories.txt
valdazpack/data/poser/poser_file_extensions.txt
valdazpack/data/schemas/djl.schema.json
valdazpack/data/schemas/dson.schema.json
valdazpack/data/schemas/Manifest.xsd
valdazpack/data/schemas/Metadata.xsd
valdazpack/data/schemas/Supplement.xsd
valdazpack/data/templates/report.css
valdazpack/data/templates/report.html.jinja
valdazpack/data/templates/report.js
valdazpack/data/templates/report.txt.jinja
valdazpack/issues/__init__.py
valdazpack/issues/contentdirectory.py
valdazpack/issues/data.py
valdazpack/issues/dsonfiles.py
valdazpack/issues/geometries.py
valdazpack/issues/libraries.py
valdazpack/issues/manifest.py
valdazpack/issues/metadatafile.py
valdazpack/issues/package.py
valdazpack/issues/runtime.py
valdazpack/issues/supplementfile.py
valdazpack/issues/support.py
valdazpack/issues/zipfile.py
valdazpack/rules/__init__.py
valdazpack/rules/contentdirectory.py
valdazpack/rules/datadirectory.py
valdazpack/rules/dsonfiles.py
valdazpack/rules/metadatafiles.py
valdazpack/rules/package.py
valdazpack/rules/packagemanifest.py
valdazpack/rules/packagesupplementfile.py
valdazpack/rules/runtimedirectory.py
valdazpack/rules/runtimegeometriesdirectory.py
valdazpack/rules/runtimelibrariesdirectory.py
valdazpack/rules/runtimesupportdirectory.py
valdazpack/rules/zipfile.py
valdazpack/validator/__init__.py
valdazpack-0.1.1.dist-info/entry_points.txt
valdazpack-0.1.1.dist-info/LICENSE
valdazpack-0.1.1.dist-info/METADATA
valdazpack-0.1.1.dist-info/WHEEL
valdazpack-0.1.1.dist-info/RECORD
